openpay/__init__.py
openpay/new_checkout.py
openpay/payload.py
openpay/payment_decorators.py
openpay/utils.py
python_openpay-0.6.3.dist-info/LICENCE
python_openpay-0.6.3.dist-info/METADATA
python_openpay-0.6.3.dist-info/WHEEL
python_openpay-0.6.3.dist-info/top_level.txt
python_openpay-0.6.3.dist-info/RECORD
