Metadata-Version: 2.1
Name: python-openpay
Version: 0.6.3
Summary: openpay python sdk
Home-page: https://github.com/openpaygithub/PythonSDK
Author: openpay
Author-email: pythondev@openpay.com.au
License: UNKNOWN
Platform: UNKNOWN
Classifier: Programming Language :: Python :: 3
Classifier: Programming Language :: Python :: 2
Classifier: License :: OSI Approved :: MIT License
Classifier: Operating System :: OS Independent
Requires-Dist: lxml
Requires-Dist: requests (==2.20.1)
